iflow_mcp_crypto_technical_analysis_indi-0.2.0.dist-info/licenses/LICENSE
mcp_gateway/__init__.py
mcp_gateway/__main__.py
mcp_gateway/loader.py
mcp_gateway/server.py
mcp_gateway/data/config.yaml
iflow_mcp_crypto_technical_analysis_indi-0.2.0.dist-info/METADATA
iflow_mcp_crypto_technical_analysis_indi-0.2.0.dist-info/WHEEL
iflow_mcp_crypto_technical_analysis_indi-0.2.0.dist-info/entry_points.txt
iflow_mcp_crypto_technical_analysis_indi-0.2.0.dist-info/top_level.txt
iflow_mcp_crypto_technical_analysis_indi-0.2.0.dist-info/RECORD
