Metadata-Version: 2.4
Name: iflow-mcp-crypto_technical_analysis_indi
Version: 0.2.0
Summary: Cryptocurrency Technical Analysis Indicator for trading APIs in finance are mapped to binance's kline api empower's traders with comprehensive tools for cryptocurrency trading, delivering accurate values for key indicators such as Relative Strength Index (RSI), Bollinger Bands, Exponential Moving Average (EMA), Moving Average Convergence Divergence (MACD), Simple Moving Average (SMA), Money Flow Index (MFI), Stochastic Oscillator, Parabolic SAR, Average Directional Index (ADX), Volume O
Requires-Python: >=3.10
License-File: LICENSE
Requires-Dist: mcp>=1.6.0
Requires-Dist: pyyaml>=6.0.2
Requires-Dist: jinja2>=3.0.0
Dynamic: license-file
